vvxme/__init__.py
vvxme/__main__.py
vvxme/vvxme.py
vvxme/data/pdmssp.cfg.example
vvxme/menu/__init__.py
vvxme/menu/device_infomation_submenu.py
vvxme/menu/device_management_submenu.py
vvxme/menu/menu_commons.py
vvxme/menu/quick_configuration_submenu.py
vvxme/menu/selection_menu.py
vvxme/menu/simulate_key_events_submenu.py
vvxme/menu/web_call_controls_submenu.py
vvxme-1.1.0.post2.dist-info/LICENSE.txt
vvxme-1.1.0.post2.dist-info/METADATA
vvxme-1.1.0.post2.dist-info/WHEEL
vvxme-1.1.0.post2.dist-info/entry_points.txt
vvxme-1.1.0.post2.dist-info/top_level.txt
vvxme-1.1.0.post2.dist-info/RECORD
