Metadata-Version: 2.1
Name: vvxme
Version: 1.1.0.post2
Summary: Manages your Poly VVX powered by RESTAPIs based on (UCS>=6.1) directly or now via PDMS-SP!, with CLI Menu or simply use the available VVX class to develop your own applications.
Home-page: https://github.com/eupubs/vvxme.git
Author: Eu Boon Lee
Author-email: boonlee.eu@poly.com
License: MIT
Keywords: poly polycom vvx
Platform: UNKNOWN
Classifier: Development Status :: 5 - Production/Stable
Classifier: License :: OSI Approved :: MIT License
Classifier: Programming Language :: Python :: 3.5
Classifier: Programming Language :: Python :: 3.6
Classifier: Programming Language :: Python :: 3.7
Requires-Python: >=3.5
Requires-Dist: datetime
Requires-Dist: ipaddress
Requires-Dist: json5
Requires-Dist: keyboard
Requires-Dist: requests
Requires-Dist: configparser
